<?xml version="1.0"?>
<odoo>
    <menuitem id="estate_menu_root" name="Real Estate">
        <menuitem id="first_advertisements" name="Advertisements">
            <menuitem id="second_estate_property" action="estate_property_action" />
        </menuitem>
        <menuitem id="first_settings" name="Settings">
            <menuitem id="second_estate_property_type" action="estate_property_type_action" />
            <menuitem id="second_estate_property_tag" action="estate_property_tag_action" />
        </menuitem>
    </menuitem>
</odoo>